pyfabricops/__init__.py
pyfabricops/_version.py
pyfabricops/api/__init__.py
pyfabricops/api/api.py
pyfabricops/api/auth.py
pyfabricops/api/scopes.py
pyfabricops/cd/__init__.py
pyfabricops/cd/support_files.py
pyfabricops/core/__init__.py
pyfabricops/core/capacities.py
pyfabricops/core/connections.py
pyfabricops/core/deployment_pipelines.py
pyfabricops/core/domains.py
pyfabricops/core/folders.py
pyfabricops/core/gateways.py
pyfabricops/core/gateways_encryp_creds.py
pyfabricops/core/git.py
pyfabricops/core/tags.py
pyfabricops/core/workspaces.py
pyfabricops/dmv/__init__.py
pyfabricops/dmv/dmv.py
pyfabricops/helpers/__init__.py
pyfabricops/helpers/data_pipelines.py
pyfabricops/helpers/dataflows_gen1.py
pyfabricops/helpers/dataflows_gen2.py
pyfabricops/helpers/environments.py
pyfabricops/helpers/folders.py
pyfabricops/helpers/items.py
pyfabricops/helpers/lakehouses.py
pyfabricops/helpers/notebooks.py
pyfabricops/helpers/reports.py
pyfabricops/helpers/semantic_models.py
pyfabricops/helpers/warehouses.py
pyfabricops/helpers/workspaces.py
pyfabricops/items/__init__.py
pyfabricops/items/data_pipelines.py
pyfabricops/items/dataflows_gen1.py
pyfabricops/items/dataflows_gen2.py
pyfabricops/items/environments.py
pyfabricops/items/items.py
pyfabricops/items/lakehouses.py
pyfabricops/items/notebooks.py
pyfabricops/items/reports.py
pyfabricops/items/semantic_models.py
pyfabricops/items/shortcuts.py
pyfabricops/items/spark.py
pyfabricops/items/variable_libraries.py
pyfabricops/items/warehouses.py
pyfabricops/utils/__init__.py
pyfabricops/utils/decorators.py
pyfabricops/utils/exceptions.py
pyfabricops/utils/logging.py
pyfabricops/utils/schemas.py
pyfabricops/utils/utils.py
pyfabricops-0.3.4.dist-info/METADATA
pyfabricops-0.3.4.dist-info/WHEEL
pyfabricops-0.3.4.dist-info/licenses/LICENSE
pyfabricops-0.3.4.dist-info/RECORD
