Metadata-Version: 2.4
Name: pyfabricops
Version: 0.3.4
Summary: A Python wrapper library for Microsoft Fabric and Power BI that provides a simple, consistent interface to the official Fabric REST APIs, with automatic fallback to Power BI REST APIs when required. Designed to run in Fabric notebooks, pure Python scripts, or as part of YAML-based CI/CD workflows.
License-Expression: MIT
License-File: LICENSE
Author: alisonpezzott
Author-email: alisonpezzott@gmail.com
Requires-Python: >=3.10, <= 3.13
Classifier: Development Status :: 3 - Alpha
Classifier: Intended Audience :: Developers
Classifier: License :: OSI Approved :: MIT License
Classifier: Programming Language :: Python :: 3.10
Classifier: Programming Language :: Python :: 3.11
Classifier: Programming Language :: Python :: 3.12
Classifier: Operating System :: OS Independent
Classifier: Environment :: Console
Classifier: Framework :: Jupyter
Classifier: Framework :: IPython
Classifier: Intended Audience :: System Administrators
Classifier: Topic :: Software Development :: Libraries
Classifier: Topic :: Software Development :: Testing
Classifier: Topic :: Software Development :: Build Tools
Classifier: Topic :: Education
Classifier: Topic :: Scientific/Engineering :: Information Analysis
Requires-Dist: azure-identity (==1.16.0)
Requires-Dist: azure-storage-blob (==12.25.1)
Requires-Dist: cryptography (>=3.4.8,<47.0.0)
Requires-Dist: json5 (==0.9.28)
Requires-Dist: pandas (==2.3.0)
Requires-Dist: pyadomd (>=0.1.1)
Requires-Dist: python-dotenv (==1.1.1)
Requires-Dist: pythonnet (>=3.0.0)
Requires-Dist: requests (==2.32.4)
Project-URL: Docs, https://pyfabricops.readthedocs.io/en/latest/
Project-URL: Examples, https://github.com/alisonpezzott/pyfabricops-examples.git
Project-URL: Issues, https://github.com/alisonpezzott/pyfabricops/issues
Project-URL: Repository, https://github.com/alisonpezzott/pyfabricops.git
